perfectreports/main_cli.py
perfectreports/temp.py
perfectreports/py/analytics.py
perfectreports/py/commands_api.py
perfectreports/py/custom_reasons.py
perfectreports/py/functions.py
perfectreports/py/html.py
perfectreports/py/integrations/teams.py
perfectreportstest-0.0.12.dist-info/METADATA
perfectreportstest-0.0.12.dist-info/WHEEL
perfectreportstest-0.0.12.dist-info/entry_points.txt
perfectreportstest-0.0.12.dist-info/top_level.txt
perfectreportstest-0.0.12.dist-info/RECORD
