Metadata-Version: 2.1
Name: perfectreportstest
Version: 0.0.12
Summary: Custom Reports
Author-email: Genesis Thomas <genesis.thomas@perforce.com>
Classifier: Programming Language :: Python :: 3
Classifier: Operating System :: OS Independent
Requires-Python: >=3.8
Requires-Dist: requests ==2.31.0
Requires-Dist: pandas ==2.0.3
Requires-Dist: matplotlib ==3.7.1
Requires-Dist: plotly ==5.14.1
Requires-Dist: kaleido ==0.2.1
Requires-Dist: numpy ==1.24.3
Requires-Dist: sweetviz ==2.3.1
Requires-Dist: bs4 ==0.0.1
Requires-Dist: asyncio ==3.4.3
Requires-Dist: pymsteams ==0.2.2
Requires-Dist: statsmodels ==0.14.0
